Metadata-Version: 2.4
Name: githooklib
Version: 1.1.0
Summary: A Python framework (and CLI) for creating, managing, and installing Git hooks with python
Author-email: danielnachumdev <danielnachumdev@gmail.com>
License: MIT License
Project-URL: Homepage, https://github.com/danielnachumdev/githooklib
Project-URL: Bug Tracker, https://github.com/danielnachumdev/githooklib/issues
Classifier: Development Status :: 3 - Alpha
Classifier: Intended Audience :: Developers
Classifier: Programming Language :: Python :: 3
Classifier: Operating System :: Microsoft :: Windows
Requires-Python: >=3.8.0
License-File: LICENSE
Requires-Dist: fire
Dynamic: license-file
